_tox_pyenv_redux/__init__.py
_tox_pyenv_redux/plugin.py
tox_pyenv_redux-1.1.0.dist-info/LICENSE
tox_pyenv_redux-1.1.0.dist-info/METADATA
tox_pyenv_redux-1.1.0.dist-info/WHEEL
tox_pyenv_redux-1.1.0.dist-info/entry_points.txt
tox_pyenv_redux-1.1.0.dist-info/top_level.txt
tox_pyenv_redux-1.1.0.dist-info/zip-safe
tox_pyenv_redux-1.1.0.dist-info/RECORD
