Metadata-Version: 2.1
Name: tox-pyenv-redux
Version: 1.1.0
Summary: A tox Python discovery plugin for pyenv-installed interpreters
Author-email: Dmitry Meyer <me@undef.im>
License: MIT
Project-URL: Homepage, https://github.com/un-def/tox-pyenv-redux
Project-URL: Repository, https://github.com/un-def/tox-pyenv-redux.git
Project-URL: Changelog, https://github.com/un-def/tox-pyenv-redux/releases
Project-URL: Issues, https://github.com/un-def/tox-pyenv-redux/issues
Keywords: tox,pyenv
Classifier: Development Status :: 4 - Beta
Classifier: License :: OSI Approved :: MIT License
Classifier: Intended Audience :: Developers
Classifier: Framework :: tox
Classifier: Topic :: Software Development :: Libraries
Classifier: Topic :: Software Development :: Testing
Classifier: Topic :: Utilities
Classifier: Programming Language :: Python :: 3
Classifier: Programming Language :: Python :: 3.8
Classifier: Programming Language :: Python :: 3.9
Classifier: Programming Language :: Python :: 3.10
Classifier: Programming Language :: Python :: 3.11
Classifier: Programming Language :: Python :: 3.12
Requires-Python: >=3.8
License-File: LICENSE
Requires-Dist: tox >=4
Requires-Dist: virtualenv-pyenv <0.6,>=0.5
